Metadata-Version: 2.4
Name: acryl-executor-dev
Version: 0.1.4
Summary: An library used within Acryl Agents to execute tasks
Home-page: https://datahubproject.io/
License: Apache License 2.0
Project-URL: Documentation, https://datahubproject.io/docs/
Project-URL: Source, https://github.com/linkedin/datahub
Project-URL: Changelog, https://github.com/linkedin/datahub/releases
Classifier: Programming Language :: Python
Classifier: Programming Language :: Python :: 3
Classifier: Programming Language :: Python :: 3 :: Only
Classifier: Programming Language :: Python :: 3.7
Classifier: Programming Language :: Python :: 3.8
Classifier: Programming Language :: Python :: 3.9
Classifier: Programming Language :: Python :: 3.10
Classifier: Intended Audience :: Developers
Classifier: Intended Audience :: Information Technology
Classifier: Intended Audience :: System Administrators
Classifier: License :: OSI Approved
Classifier: License :: OSI Approved :: Apache Software License
Classifier: Operating System :: Unix
Classifier: Operating System :: POSIX :: Linux
Classifier: Environment :: Console
Classifier: Environment :: MacOS X
Classifier: Topic :: Software Development
Requires-Python: >=3.7
License-File: LICENSE
Requires-Dist: botocore!=1.23.0
Requires-Dist: typing_extensions>=3.7.4; python_version < "3.11"
Requires-Dist: sqlalchemy-stubs>=0.4
Requires-Dist: mypy_extensions>=0.4.3
Requires-Dist: pydantic>=1.5.1
Requires-Dist: acryl-datahub[datahub-rest]>=0.13.3.4rc2
Requires-Dist: boto3
Provides-Extra: dev
Requires-Dist: flake8>=3.8.3; extra == "dev"
Requires-Dist: mypy<0.920,>=0.901; extra == "dev"
Requires-Dist: types-dataclasses; extra == "dev"
Requires-Dist: pydantic>=1.5.1; extra == "dev"
Requires-Dist: types-python-dateutil; extra == "dev"
Requires-Dist: types-PyYAML; extra == "dev"
Requires-Dist: typing_extensions>=3.7.4; python_version < "3.11" and extra == "dev"
Requires-Dist: pytest>=6.2.2; extra == "dev"
Requires-Dist: freezegun; extra == "dev"
Requires-Dist: requests-mock; extra == "dev"
Requires-Dist: types-freezegun; extra == "dev"
Requires-Dist: botocore!=1.23.0; extra == "dev"
Requires-Dist: sqlalchemy-stubs>=0.4; extra == "dev"
Requires-Dist: mypy_extensions>=0.4.3; extra == "dev"
Requires-Dist: flake8-tidy-imports>=4.3.0; extra == "dev"
Requires-Dist: acryl-datahub[datahub-rest]>=0.13.3.4rc2; extra == "dev"
Requires-Dist: types-toml; extra == "dev"
Requires-Dist: boto3; extra == "dev"
Requires-Dist: types-requests; extra == "dev"
Dynamic: classifier
Dynamic: description
Dynamic: description-content-type
Dynamic: home-page
Dynamic: license
Dynamic: license-file
Dynamic: project-url
Dynamic: provides-extra
Dynamic: requires-dist
Dynamic: requires-python
Dynamic: summary
